opentf/tools/ctl.py
opentf/tools/ctlattachments.py
opentf/tools/ctlcommons.py
opentf/tools/ctlcompletion.py
opentf/tools/ctlconfig.py
opentf/tools/ctldatasources.py
opentf/tools/ctlgenerate.py
opentf/tools/ctlnetworking.py
opentf/tools/ctlplugin_gitlab.py
opentf/tools/ctlqualitygate.py
opentf/tools/ctltokens.py
opentf/tools/ctlworkflows.py
opentf/tools/done.py
opentf/tools/ready.py
opentf_tools-0.54.0.dist-info/licenses/LICENSE
opentf_tools-0.54.0.dist-info/METADATA
opentf_tools-0.54.0.dist-info/WHEEL
opentf_tools-0.54.0.dist-info/entry_points.txt
opentf_tools-0.54.0.dist-info/top_level.txt
opentf_tools-0.54.0.dist-info/RECORD
