Metadata-Version: 2.4
Name: opentf-tools
Version: 0.54.0
Summary: OpenTestFactory Orchestrator Tools
Home-page: https://opentestfactory.org/tools/
Author: Martin Lafaix
Author-email: mlafaix@henix.com
Maintainer: Henix
Maintainer-email: opentestfactory@henix.com
License: Apache Software License (https://www.apache.org/licenses/LICENSE-2.0)
Classifier: Development Status :: 4 - Beta
Classifier: Programming Language :: Python :: 3
Classifier: Operating System :: OS Independent
Classifier: Topic :: Utilities
Classifier: License :: OSI Approved :: Apache Software License
Requires-Python: >= 3.8.0
License-File: LICENSE
Requires-Dist: requests>=2.31
Requires-Dist: PyJWT[crypto]>=2.7
Requires-Dist: PyYAML>=6
Provides-Extra: docker
Requires-Dist: docker>=5.0; extra == "docker"
Dynamic: author
Dynamic: author-email
Dynamic: classifier
Dynamic: description
Dynamic: description-content-type
Dynamic: home-page
Dynamic: license
Dynamic: license-file
Dynamic: maintainer
Dynamic: maintainer-email
Dynamic: provides-extra
Dynamic: requires-dist
Dynamic: requires-python
Dynamic: summary
